Metadata-Version: 2.1
Name: bospm
Version: 0.1.1
Summary: Bellande Operating System Package Manager
Author: Ronaldson Bellande
Author-email: ronaldsonbellande@gmail.com
License: GNU General Public License v3 or later (GPLv3+)
Project-URL: Home, https://github.com/Architecture-Mechanism/bellande_operating_system_package_manager
Project-URL: Bug Reports, https://github.com/Architecture-Mechanism/bellande_operating_system_package_manager/issues
Project-URL: Source, https://github.com/Architecture-Mechanism/bellande_operating_system_package_manager
Platform: any
Classifier: Development Status :: 3 - Alpha
Classifier: Intended Audience :: Developers
Classifier: License :: OSI Approved :: GNU General Public License v3 or later (GPLv3+)
Classifier: Operating System :: OS Independent
Classifier: Programming Language :: Python :: 2
Classifier: Programming Language :: Python :: 2.7
Classifier: Programming Language :: Python :: 3
Classifier: Programming Language :: Python :: 3.6
Classifier: Programming Language :: Python :: 3.7
Classifier: Programming Language :: Python :: 3.8
Classifier: Programming Language :: Python :: 3.9
Classifier: Programming Language :: Python :: 3.10
Requires-Python: >=2.7
License-File: LICENSE
Requires-Dist: requests>=2.25.1
Provides-Extra: dev
Requires-Dist: pytest; extra == "dev"
Requires-Dist: pytest-cov[all]; extra == "dev"
Requires-Dist: mypy; extra == "dev"
Requires-Dist: black; extra == "dev"
